htoopdf/__init__.py
htoopdf/pdf2image.py
htoopdf/pdf2text.py
htoopdf-1.0.dist-info/LICENSE
htoopdf-1.0.dist-info/METADATA
htoopdf-1.0.dist-info/WHEEL
htoopdf-1.0.dist-info/top_level.txt
htoopdf-1.0.dist-info/RECORD
