Metadata-Version: 2.1
Name: htoopdf
Version: 1.0
Summary: This is the homepage of our project.
License-File: LICENSE
